nosenumpyseterr.py
setup.py
nose_numpyseterr.egg-info/PKG-INFO
nose_numpyseterr.egg-info/SOURCES.txt
nose_numpyseterr.egg-info/dependency_links.txt
nose_numpyseterr.egg-info/entry_points.txt
nose_numpyseterr.egg-info/top_level.txt