Metadata-Version: 1.0
Name: nose-numpyseterr
Version: 0.1
Summary: Nose plugin to set how floating-point errors are handled by numpy
Home-page: UNKNOWN
Author: Takafumi Arakaki
Author-email: aka.tkf@gmail.com
License: MIT License
Platform: UNKNOWN
Classifier: Development Status :: 3 - Alpha
Classifier: Intended Audience :: Science/Research
Classifier: Intended Audience :: Developers
Classifier: License :: OSI Approved :: MIT License
Classifier: Programming Language :: Python
Classifier: Topic :: Software Development :: Testing
Classifier: Topic :: Scientific/Engineering
